{
  "version": 2,
  "exported_at": "2026-05-27T17:00:00.000Z",
  "articles": [
    {
      "id": "article-001",
      "title": "AI Startups Face Funding Winter as Investors Tighten Belts",
      "theme": "Tech_News",
      "source": "TechCrunch",
      "full_text": "AI startups across the globe are facing a severe funding winter as venture capital firms tighten their belts amid economic uncertainty. Many promising young companies that flourished during the AI boom are now struggling to secure follow-up rounds. Investors are demanding clearer paths to profitability before committing new capital. Some analysts warn that the shakeout could accelerate consolidation in the sector, with larger firms acquiring distressed startups at bargain prices. However, a handful of companies with strong revenue growth and proprietary technology continue to attract premium valuations.",
      "created_at": 1716816000000
    },
    {
      "id": "article-002",
      "title": "Remote Work Debate Resurfaces as Major Banks Mandate Return to Office",
      "theme": "TOEIC_High_Freq",
      "source": "Financial Times",
      "full_text": "The debate around remote work has resurfaced as major investment banks mandate a full return to office for their employees. While some workers welcome the structure of in-person collaboration, others argue that the flexibility of hybrid arrangements has boosted both morale and productivity. Critics contend that mandatory return policies overlook the commuting burdens faced by employees in high-cost cities. Proponents insist that spontaneous meetings and mentorship opportunities are irreplaceable in an office environment. The trend has sparked renewed discussion about work-life balance and the future of corporate culture.",
      "created_at": 1716816000000
    }
  ],
  "words": [
    {
      "id": "word-001",
      "word": "severe",
      "chinese": "嚴重的",
      "part_of_speech": "adjective",
      "article_id": "article-001",
      "sentence_in_article": "AI startups across the globe are facing a severe funding winter",
      "sentence_translation": "全球的AI新創公司正面臨嚴重的資金寒冬",
      "grammar": "adjective modifying 'funding winter' — 形容詞修飾名詞",
      "tags": ["Tech_News", "IELTS_Academic"],
      "srs": { "level": 1, "interval": 2, "next_review": 1716816000000, "review_count": 0 },
      "created_at": 1716816000000
    },
    {
      "id": "word-002",
      "word": "tighten their belts",
      "chinese": "勒緊腰帶 / 縮減開支",
      "part_of_speech": "phrase",
      "article_id": "article-001",
      "sentence_in_article": "venture capital firms tighten their belts amid economic uncertainty",
      "sentence_translation": "創投公司在經濟不確定性中縮減開支",
      "grammar": "idiomatic phrase — 慣用語，比喻節約/縮減",
      "tags": ["Tech_News"],
      "srs": { "level": 0, "interval": 1, "next_review": 1716816000000, "review_count": 0 },
      "created_at": 1716816000000
    },
    {
      "id": "word-003",
      "word": "flourished",
      "chinese": "蓬勃發展",
      "part_of_speech": "verb",
      "article_id": "article-001",
      "sentence_in_article": "Many promising young companies that flourished during the AI boom",
      "sentence_translation": "許多在AI熱潮中蓬勃發展的有前景的新創公司",
      "grammar": "past participle — 過去分詞，修飾 companies",
      "tags": ["Tech_News", "IELTS_Academic"],
      "srs": { "level": 0, "interval": 1, "next_review": 1716816000000, "review_count": 0 },
      "created_at": 1716816000000
    },
    {
      "id": "word-004",
      "word": "consolidation",
      "chinese": "整合 / 合併",
      "part_of_speech": "noun",
      "article_id": "article-001",
      "sentence_in_article": "the shakeout could accelerate consolidation in the sector",
      "sentence_translation": "市場洗牌可能加速該領域的整合",
      "grammar": "noun used as object — 名詞作賓語",
      "tags": ["Tech_News", "TOEIC_High_Freq"],
      "srs": { "level": 0, "interval": 1, "next_review": 1716816000000, "review_count": 0 },
      "created_at": 1716816000000
    },
    {
      "id": "word-005",
      "word": "distressed",
      "chinese": "陷入困境的",
      "part_of_speech": "adjective",
      "article_id": "article-001",
      "sentence_in_article": "acquiring distressed startups at bargain prices",
      "sentence_translation": "以低價收購陷入困境的新創公司",
      "grammar": "adjective modifying 'startups' — 形容詞修飾新創公司",
      "tags": ["Tech_News"],
      "srs": { "level": 0, "interval": 1, "next_review": 1716816000000, "review_count": 0 },
      "created_at": 1716816000000
    },
    {
      "id": "word-006",
      "word": "premium valuations",
      "chinese": "溢價估值",
      "part_of_speech": "noun",
      "article_id": "article-001",
      "sentence_in_article": "continue to attract premium valuations",
      "sentence_translation": "繼續吸引溢價估值",
      "grammar": "noun phrase — 名詞片語",
      "tags": ["Tech_News", "TOEIC_High_Freq"],
      "srs": { "level": 0, "interval": 1, "next_review": 1716816000000, "review_count": 0 },
      "created_at": 1716816000000
    },
    {
      "id": "word-007",
      "word": "resurfaced",
      "chinese": "重新浮現 / 再次成為焦點",
      "part_of_speech": "verb",
      "article_id": "article-002",
      "sentence_in_article": "The debate around remote work has resurfaced",
      "sentence_translation": "關於遠距工作的辯論重新浮現",
      "grammar": "present perfect — 現在完成式，強調過去到現在的影響",
      "tags": ["TOEIC_High_Freq", "IELTS_Academic"],
      "srs": { "level": 0, "interval": 1, "next_review": 1716816000000, "review_count": 0 },
      "created_at": 1716816000000
    },
    {
      "id": "word-008",
      "word": "mandate",
      "chinese": "強制要求",
      "part_of_speech": "verb",
      "article_id": "article-002",
      "sentence_in_article": "major investment banks mandate a full return to office",
      "sentence_translation": "大型投資銀行強制要求全面回歸辦公室",
      "grammar": "verb used in active voice — 主動語態，主詞發出動作",
      "tags": ["TOEIC_High_Freq"],
      "srs": { "level": 0, "interval": 1, "next_review": 1716816000000, "review_count": 0 },
      "created_at": 1716816000000
    },
    {
      "id": "word-009",
      "word": "hybrid arrangements",
      "chinese": "混合制安排",
      "part_of_speech": "noun",
      "article_id": "article-002",
      "sentence_in_article": "the flexibility of hybrid arrangements has boosted both morale and productivity",
      "sentence_translation": "混合制安排的靈活性提升了士氣和生產力",
      "grammar": "noun phrase as subject — 名詞片語做主詞",
      "tags": ["TOEIC_High_Freq"],
      "srs": { "level": 0, "interval": 1, "next_review": 1716816000000, "review_count": 0 },
      "created_at": 1716816000000
    },
    {
      "id": "word-010",
      "word": "contend",
      "chinese": "主張 / 爭辯",
      "part_of_speech": "verb",
      "article_id": "article-002",
      "sentence_in_article": "Critics contend that mandatory return policies overlook the commuting burdens",
      "sentence_translation": "批評者主張強制回歸政策忽略了通勤負擔",
      "grammar": "verb followed by 'that' clause — 及物動詞接 that 子句",
      "tags": ["TOEIC_High_Freq", "IELTS_Academic"],
      "srs": { "level": 0, "interval": 1, "next_review": 1716816000000, "review_count": 0 },
      "created_at": 1716816000000
    },
    {
      "id": "word-011",
      "word": "overlook",
      "chinese": "忽略 / 忽視",
      "part_of_speech": "verb",
      "article_id": "article-002",
      "sentence_in_article": "overlook the commuting burdens faced by employees",
      "sentence_translation": "忽略了員工面臨的通勤負擔",
      "grammar": "transitive verb + object — 及物動詞接受詞",
      "tags": ["TOEIC_High_Freq"],
      "srs": { "level": 0, "interval": 1, "next_review": 1716816000000, "review_count": 0 },
      "created_at": 1716816000000
    },
    {
      "id": "word-012",
      "word": "irreplaceable",
      "chinese": "無可替代的",
      "part_of_speech": "adjective",
      "article_id": "article-002",
      "sentence_in_article": "spontaneous meetings and mentorship opportunities are irreplaceable",
      "sentence_translation": "自發性會議和指導機會是無可替代的",
      "grammar": "adjective as complement — 形容詞作補語，與 be 動詞連用",
      "tags": ["TOEIC_High_Freq"],
      "srs": { "level": 0, "interval": 1, "next_review": 1716816000000, "review_count": 0 },
      "created_at": 1716816000000
    },
    {
      "id": "word-013",
      "word": "spontaneous",
      "chinese": "自發性的 / 自然的",
      "part_of_speech": "adjective",
      "article_id": "article-002",
      "sentence_in_article": "spontaneous meetings and mentorship opportunities",
      "sentence_translation": "自發性的會議和指導機會",
      "grammar": "adjective modifying 'meetings' — 形容詞修飾會議",
      "tags": ["IELTS_Academic"],
      "srs": { "level": 0, "interval": 1, "next_review": 1716816000000, "review_count": 0 },
      "created_at": 1716816000000
    },
    {
      "id": "word-014",
      "word": "proponent",
      "chinese": "支持者",
      "part_of_speech": "noun",
      "article_id": "article-002",
      "sentence_in_article": "Proponents insist that spontaneous meetings are irreplaceable",
      "sentence_translation": "支持者堅持自發性會議無可替代",
      "grammar": "noun as subject — 名詞作主詞",
      "tags": ["TOEIC_High_Freq"],
      "srs": { "level": 0, "interval": 1, "next_review": 1716816000000, "review_count": 0 },
      "created_at": 1716816000000
    },
    {
      "id": "word-015",
      "word": "commuting burden",
      "chinese": "通勤負擔",
      "part_of_speech": "noun",
      "article_id": "article-002",
      "sentence_in_article": "commuting burdens faced by employees in high-cost cities",
      "sentence_translation": "高成本城市員工面臨的通勤負擔",
      "grammar": "noun phrase — 名詞片語",
      "tags": ["TOEIC_High_Freq"],
      "srs": { "level": 0, "interval": 1, "next_review": 1716816000000, "review_count": 0 },
      "created_at": 1716816000000
    }
  ]
}
